doorstop/__init__.py
doorstop/cli/__init__.py
doorstop/cli/commands.py
doorstop/cli/main.py
doorstop/cli/utilities.py
doorstop/common.py
doorstop/core/__init__.py
doorstop/core/base.py
doorstop/core/builder.py
doorstop/core/document.py
doorstop/core/editor.py
doorstop/core/exporter.py
doorstop/core/files/templates/html/bootstrap.bundle.min.js
doorstop/core/files/templates/html/bootstrap.min.css
doorstop/core/files/templates/html/doorstop.css
doorstop/core/files/templates/html/general.css
doorstop/core/files/templates/html/jquery.min.js
doorstop/core/files/templates/html/logo-black-white.png
doorstop/core/files/templates/html/output/chtml/fonts/tex.js
doorstop/core/files/templates/html/output/chtml/fonts/woff-v2/MathJax_AMS-Regular.woff
doorstop/core/files/templates/html/output/chtml/fonts/woff-v2/MathJax_Calligraphic-Bold.woff
doorstop/core/files/templates/html/output/chtml/fonts/woff-v2/MathJax_Calligraphic-Regular.woff
doorstop/core/files/templates/html/output/chtml/fonts/woff-v2/MathJax_Fraktur-Bold.woff
doorstop/core/files/templates/html/output/chtml/fonts/woff-v2/MathJax_Fraktur-Regular.woff
doorstop/core/files/templates/html/output/chtml/fonts/woff-v2/MathJax_Main-Bold.woff
doorstop/core/files/templates/html/output/chtml/fonts/woff-v2/MathJax_Main-Italic.woff
doorstop/core/files/templates/html/output/chtml/fonts/woff-v2/MathJax_Main-Regular.woff
doorstop/core/files/templates/html/output/chtml/fonts/woff-v2/MathJax_Math-BoldItalic.woff
doorstop/core/files/templates/html/output/chtml/fonts/woff-v2/MathJax_Math-Italic.woff
doorstop/core/files/templates/html/output/chtml/fonts/woff-v2/MathJax_Math-Regular.woff
doorstop/core/files/templates/html/output/chtml/fonts/woff-v2/MathJax_SansSerif-Bold.woff
doorstop/core/files/templates/html/output/chtml/fonts/woff-v2/MathJax_SansSerif-Italic.woff
doorstop/core/files/templates/html/output/chtml/fonts/woff-v2/MathJax_SansSerif-Regular.woff
doorstop-3.1.dist-info/METADATA
doorstop-3.1.dist-info/WHEEL
doorstop-3.1.dist-info/entry_points.txt
doorstop-3.1.dist-info/licenses/LICENSE.md
doorstop-3.1.dist-info/RECORD
