Metadata-Version: 2.4
Name: doorstop
Version: 3.1
Summary: Requirements management using version control.
License: LGPLv3
License-File: LICENSE.md
Keywords: requirements-management,version-control,documentation,traceability,markdown,certification,html
Author: Jace Browning
Author-email: jacebrowning@gmail.com
Requires-Python: >=3.10,<3.15
Classifier: Development Status :: 5 - Production/Stable
Classifier: Environment :: Console
Classifier: License :: OSI Approved :: GNU Lesser General Public License v3 (LGPLv3)
Classifier: License :: Other/Proprietary License
Classifier: Operating System :: OS Independent
Classifier: Programming Language :: Python
Classifier: Programming Language :: Python :: 3
Classifier: Programming Language :: Python :: 3.10
Classifier: Programming Language :: Python :: 3.11
Classifier: Programming Language :: Python :: 3.12
Classifier: Programming Language :: Python :: 3.13
Classifier: Programming Language :: Python :: 3.14
Classifier: Topic :: Software Development :: Documentation
Classifier: Topic :: Text Editors :: Documentation
Classifier: Topic :: Text Processing :: Markup
Requires-Dist: bottle (>=0.13.4,<0.14.0)
Requires-Dist: markdown (>=3.3.3,<4.0.0)
Requires-Dist: openpyxl (>=3.1.2)
Requires-Dist: plantuml-markdown (>=3.4.2,<4.0.0)
Requires-Dist: python-frontmatter (>=1.0,<2.0)
Requires-Dist: python-markdown-math (>=0.6,<0.7)
Requires-Dist: pyyaml (>=6.0,<7.0)
Requires-Dist: requests (>=2.0,<3.0)
Requires-Dist: six
Requires-Dist: verchew (>=3.4.2,<4.0.0)
Project-URL: Documentation, https://doorstop.readthedocs.io
Project-URL: Homepage, https://pypi.org/project/Doorstop
Project-URL: Repository, https://github.com/doorstop-dev/doorstop
